parse_1099/__init__.py
parse_1099/__main__.py
parse_1099/__version__.py
parse_1099/main.py
parse_1099/parser.py
parse_1099/pdf_contents.py
parse_1099/subparser_interface.py
parse_1099/dividends/__init__.py
parse_1099/dividends/dividend_analyzer.py
parse_1099/dividends/dividends_interface.py
parse_1099/dividends/dividends_repository_interface.py
parse_1099/dividends/v1/__init__.py
parse_1099/dividends/v1/dividends.py
parse_1099/dividends/v1/dividends_parser.py
parse_1099/dividends/v1/dividends_repository.py
parse_1099/dividends/v1/dividends_total.py
parse_1099/sales/__init__.py
parse_1099/sales/sales_interface.py
parse_1099/sales/v1/__init__.py
parse_1099/sales/v1/sales.py
parse_1099/sales/v1/sales_parser.py
parse_1099/sales/v1/sales_total.py
parse_1099/utilities/__init__.py
parse_1099/utilities/csv_writer.py
parse_1099-2.1.2.dist-info/LICENSE
parse_1099-2.1.2.dist-info/METADATA
parse_1099-2.1.2.dist-info/WHEEL
parse_1099-2.1.2.dist-info/entry_points.txt
parse_1099-2.1.2.dist-info/top_level.txt
parse_1099-2.1.2.dist-info/RECORD
