Metadata-Version: 2.1
Name: parse_1099
Version: 2.1.2
Summary: Parses 1099 tax document (1099-B, 1099-INT, 1099-DIV) from PDF into CSV format and performs simple analysis
Home-page: 
Author: Andrew Wells, Keun Tae (Kevin) Park
Author-email: ajwells@uchicago.com, kevin.park1217@gmail.com
Project-URL: Bug Reports, https://github.com/ajwells256/1099-Parser/issues
Project-URL: Source, https://github.com/ajwells256/1099-Parser
Keywords: pdf,csv,parsing,excel,spreadsheet,tax,1099
Classifier: Development Status :: 4 - Beta
Classifier: Intended Audience :: End Users/Desktop
Classifier: Intended Audience :: Financial and Insurance Industry
Classifier: Topic :: Office/Business :: Financial
Classifier: Topic :: Office/Business :: Financial :: Accounting
Classifier: Topic :: Office/Business :: Financial :: Investment
Classifier: Topic :: Office/Business :: Financial :: Spreadsheet
Classifier: Operating System :: POSIX :: Linux
Classifier: Operating System :: MacOS :: MacOS X
Classifier: Operating System :: Microsoft :: Windows :: Windows 10
Classifier: License :: OSI Approved :: GNU Affero General Public License v3
Classifier: Programming Language :: Python :: 3
Classifier: Programming Language :: Python :: 3.6
Classifier: Programming Language :: Python :: 3.7
Classifier: Programming Language :: Python :: 3.8
Classifier: Programming Language :: Python :: 3.9
Classifier: Programming Language :: Python :: 3 :: Only
Requires-Python: >=3.6, <4
License-File: LICENSE
Requires-Dist: pdfreader >=0.1.9
Requires-Dist: tqdm >=4.59.0
Requires-Dist: yahooquery >=2.3.0
